VerilogTest/source/mac.sv
`timescale 1ns/1ns

module mac #(
    parameter LEN = 16,
    parameter PSUM_WIDTH = 32
)(
    input logic clk, nrst,

    input logic load_weight, clear_psum,

    input logic  [LEN-1:0] a_in, w_in, 
    input logic  [PSUM_WIDTH-1:0] psum_in,

    output logic [LEN-1:0] a_out, w_out,
    output logic [PSUM_WIDTH-1:0] psum_out

);

    logic [LEN-1:0]        weight_reg;
    logic [LEN-1:0]        w_out_reg;
    logic [2*LEN-1:0]      product;
    logic [PSUM_WIDTH-1:0] product_ext;
    logic valid_reg;

    assign product     = a_in * weight_reg;
    assign product_ext = {{(PSUM_WIDTH-2*LEN){1'b0}}, product};
    
    logic [PSUM_WIDTH-1:0] psum_reg;
    logic [LEN-1:0]        a_out_reg;
    
    assign psum_out    = psum_reg;
    assign a_out = a_out_reg;
    assign w_out = w_out_reg;

    always_ff @(posedge clk, negedge nrst) begin
        if (!nrst) begin
            weight_reg <= '0;
            psum_reg   <= '0;
            a_out_reg  <= '0;
            w_out_reg  <= '0;
        end
        else begin
            a_out_reg <= a_in;
            w_out_reg <= w_in;

            if (load_weight)
                weight_reg <= w_in;

            if (clear_psum)
                psum_reg <= psum_in;     
            else
                psum_reg <= psum_in + product_ext;  
        end
    end

endmodule

VerilogTest/source/mac_array.sv
`timescale 1ns/1ns

module mac_array 
#( parameter DIM = 2,
   parameter LEN = 16,
   parameter PSUM_WIDTH  = 32
)
(
    input  logic                     clk,
    input  logic                     nrst,
    input  logic                     load_weight,
    input  logic                     clear_psum,
    input  logic [LEN-1:0]          ain  [0:DIM-1],
    input  logic [LEN-1:0]          win  [0:DIM-1],
    input  logic [PSUM_WIDTH-1:0]   cin  [0:DIM-1],
    output logic [LEN-1:0]          aout [0:DIM-1],
    output logic [PSUM_WIDTH-1:0]   cout [0:DIM-1]
);

    // -------------------------
    // All signal declarations first
    // -------------------------
    logic [LEN-1:0]        ain_skewed [0:DIM-1];
    logic                  lw_skewed  [0:DIM-1];
    logic [DIM-2:0]        lw_pipe;

    logic [LEN-1:0]        a_sig    [0:DIM-1][0:DIM-1];
    logic [LEN-1:0]        w_sig    [0:DIM-1][0:DIM-1];
    logic [PSUM_WIDTH-1:0] psum_sig [0:DIM-1][0:DIM-1];

    // -------------------------
    // Activation skew
    // -------------------------
    assign ain_skewed[0] = ain[0];

    genvar s, d;
    generate
        for (s = 1; s < DIM; s++) begin : skew_row
            logic [LEN-1:0] ain_skew_chain [0:s-1];

            always_ff @(posedge clk, negedge nrst) begin
                if (!nrst) ain_skew_chain[0] <= '0;
                else       ain_skew_chain[0] <= ain[s];
            end

            for (d = 1; d < s; d++) begin : skew_chain_stage
                always_ff @(posedge clk, negedge nrst) begin
                    if (!nrst) ain_skew_chain[d] <= '0;
                    else       ain_skew_chain[d] <= ain_skew_chain[d-1];
                end
            end

            assign ain_skewed[s] = ain_skew_chain[s-1];
        end
    endgenerate

    // Replace lw_pipe and the lw_assign generate entirely with this:
    //logic lw_skewed [0:DIM-1];
    logic lw_d1;   // load_weight delayed 1 cycle
    logic lw_d2;   // load_weight delayed 2 cycles — add more for larger DIM

    always_ff @(posedge clk, negedge nrst) begin
        if (!nrst) begin
            lw_d1 <= '0;
            lw_d2 <= '0;
        end else begin
            lw_d1 <= load_weight;
            lw_d2 <= lw_d1;
        end
    end

    assign lw_skewed[0] = load_weight;
    assign lw_skewed[1] = lw_d1;
    // assign lw_skewed[2] = lw_d2;  // uncomment for DIM=3
    // etc.

    // -------------------------
    // MAC array
    // -------------------------
    genvar i, j;
    generate
        for (i = 0; i < DIM; i++) begin : row
            for (j = 0; j < DIM; j++) begin : col

                logic [LEN-1:0]        a_in_local;
                logic [LEN-1:0]        w_in_local;
                logic [PSUM_WIDTH-1:0] psum_in_local;
                logic [PSUM_WIDTH-1:0] psum_pipe1;

                assign a_in_local = (j == 0) ? ain_skewed[i] : a_sig[i][j-1];
                assign w_in_local = (i == 0) ? win[j] : w_sig[i-1][j];

                if (i == 0) begin
                    assign psum_in_local = cin[j];
                end
                else begin
                    always_ff @(posedge clk, negedge nrst) begin
                        if (!nrst) psum_pipe1 <= '0;
                        else       psum_pipe1 <= psum_sig[i-1][j];
                    end
                    assign psum_in_local = psum_pipe1;
                end

                mac #(.LEN(LEN), .PSUM_WIDTH(PSUM_WIDTH)) mac_inst (
                    .clk         (clk),
                    .nrst        (nrst),
                    .load_weight (lw_skewed[i]),
                    .clear_psum  (clear_psum),
                    .a_in        (a_in_local),
                    .w_in        (w_in_local),
                    .psum_in     (psum_in_local),
                    .a_out       (a_sig[i][j]),
                    .psum_out    (psum_sig[i][j]),
                    .w_out       (w_sig[i][j])
                );
            end
        end
    endgenerate

    // -------------------------
    // Outputs
    // -------------------------
    always_comb begin
        for (int k = 0; k < DIM; k++)
            cout[k] = psum_sig[DIM-1][k];
    end

    always_comb begin
        for (int k = 0; k < DIM; k++)
            aout[k] = a_sig[k][DIM-1];
    end

endmodule

VerilogTest/source/mac_array_tb.sv

// =====================
// Testbench
// =====================
module mac_array_tb;

    parameter DIM  = 2;
    parameter LEN  = 16;
    parameter PSUM_WIDTH = 2*LEN;
    parameter PERIOD = 10;
    
    localparam LATENCY = 2*(DIM-1) + (DIM-1) + 2;  // = 3*DIM - 1, for DIM=2 gives 5

    logic clk = 0;
    logic nrst = 1;

    logic load_weight;
    logic clear_psum;

    logic [LEN-1:0]        ain   [0:DIM-1];
    logic [LEN-1:0]        win   [0:DIM-1];//[0:DIM-1];
    logic [PSUM_WIDTH-1:0] cin   [0:DIM-1];

    logic [LEN-1:0]        aout  [0:DIM-1];
    logic [PSUM_WIDTH-1:0] cout  [0:DIM-1];

    // Matrices for reference
    logic [LEN-1:0] A    [0:DIM-1][0:DIM-1];
    logic [LEN-1:0] B    [0:DIM-1][0:DIM-1];
    logic [PSUM_WIDTH-1:0] C_sw [0:DIM-1][0:DIM-1];
    logic [PSUM_WIDTH-1:0] C_hw [0:DIM-1][0:DIM-1];

    logic  valid_in_row [0:DIM-1];

    integer flush_cycles;
    integer cycle_count;

    always @(posedge clk or negedge nrst) begin
        if (!nrst) cycle_count <= 0;
        else cycle_count <= cycle_count + 1;
    end

    // Clock
    always #(PERIOD/2) clk = ~clk;

    
    mac_array #(.DIM(DIM), .LEN(LEN), .PSUM_WIDTH(PSUM_WIDTH)) dut 
    (
        .clk        (clk),
        .nrst       (nrst),
        .load_weight(load_weight),
        .clear_psum (clear_psum),
        .ain        (ain),
        .win        (win),
        .cin        (cin),
        .aout       (aout),
        .cout       (cout)
        //.valid_in_row(valid_in_row)
    );
    
    task RESETDUT;
    begin
        nrst        = 0;
        load_weight = 0;
        clear_psum  = 0;
        for (int i = 0; i < DIM; i++) begin
            ain[i] = '0;
            cin[i] = '0;
        end
        #(PERIOD);
        @(posedge clk);
        nrst = 1;
        @(posedge clk);
    end
    endtask

    task display_row(int i0);
    begin
        $display("C_hw row %0d:", i0);
        for (int j = 0; j < DIM; j++)
            $display("  C_hw[%0d][%0d] = %0d", i0, j, C_hw[i0][j]);
    end
    endtask

    task automatic compute_sw;
        for (int i = 0; i < DIM; i++)
            for (int j = 0; j < DIM; j++) begin
                C_sw[i][j] = 0;
                for (int k = 0; k < DIM; k++)
                    C_sw[i][j] += A[i][k] * B[k][j];
            end
    endtask


initial begin
    $display("CONFIG: DIM=%0d", DIM);

    $dumpfile("outputs/wave.vcd");
    $dumpvars(0, mac_array_tb);

    // Initialize matrices
    for (int i = 0; i < DIM; i++)
        for (int j = 0; j < DIM; j++) begin
            A[i][j] = LEN'(i*DIM + j + 1);
            B[i][j] = LEN'(i*DIM + j + 1);
        end

    compute_sw();
    RESETDUT();

    // -------------------------
    // Phase 1: Load Weights
    // -------------------------
    // Stream one row of B per cycle over DIM cycles.
    // Hardware lw_skewed ensures each array row latches
    // when its weight data actually arrives via w_sig chain.
    // Present row 0 data
    for (int col = 0; col < DIM; col++)
        win[col] = B[0][col];

    // Single cycle pulse — hardware skew propagates it downward
    load_weight = 1;
    @(posedge clk);
    load_weight = 0;
    $display("POST-PULSE: lw_skewed[0]=%0d lw_skewed[1]=%0d lw_pipe=%0b win=[%0d,%0d]",
            dut.lw_skewed[0], dut.lw_skewed[1], dut.lw_pipe, win[0], win[1]);
    @(posedge clk);
    $display("ROW1-LATCH: lw_skewed[0]=%0d lw_skewed[1]=%0d lw_pipe=%0b win=[%0d,%0d]",
            dut.lw_skewed[0], dut.lw_skewed[1], dut.lw_pipe, win[0], win[1]);
            
    // Continue streaming remaining rows for the wave to carry downward
    for (int row = 1; row < DIM; row++) begin
        for (int col = 0; col < DIM; col++)
            win[col] = B[row][col];
        @(posedge clk);
    end

    // Let last wave settle
    @(posedge clk);
    
    // Probe internal skew signals immediately after loading
    $display("--- lw_skewed probe ---");
    $display("  lw_skewed[0] = %0d", dut.lw_skewed[0]);
    $display("  lw_skewed[1] = %0d", dut.lw_skewed[1]);
    $display("  w_sig[0][0]  = %0d", dut.w_sig[0][0]);
    $display("  w_sig[0][1]  = %0d", dut.w_sig[0][1]);
    @(posedge clk);
    $display("--- after 1 more cycle ---");
    $display("  w_sig[0][0]  = %0d", dut.w_sig[0][0]);
    $display("  w_sig[0][1]  = %0d", dut.w_sig[0][1]);
    $display("  PE(0,0) weight_reg = %0d", dut.row[0].col[0].mac_inst.weight_reg);
    $display("  PE(0,1) weight_reg = %0d", dut.row[0].col[1].mac_inst.weight_reg);
    $display("  PE(1,0) weight_reg = %0d", dut.row[1].col[0].mac_inst.weight_reg);
    $display("  PE(1,1) weight_reg = %0d", dut.row[1].col[1].mac_inst.weight_reg);

    @(posedge clk);

    $display("--- Weight check ---");
    generate_unroll : begin
    end

    $display("  PE(0,0) weight_reg = %0d", dut.row[0].col[0].mac_inst.weight_reg);
    $display("  PE(0,1) weight_reg = %0d", dut.row[0].col[1].mac_inst.weight_reg);
    $display("  PE(1,0) weight_reg = %0d", dut.row[1].col[0].mac_inst.weight_reg);
    $display("  PE(1,1) weight_reg = %0d", dut.row[1].col[1].mac_inst.weight_reg);
    
    // -------------------------
    // Phase 2: Clear / Bias Load
    // -------------------------
    for (int i = 0; i < DIM; i++) cin[i] = '0;   // zero bias
    clear_psum = 1;
    @(posedge clk);
    clear_psum = 0;

    // -------------------------
    // Phase 3: Stream Activations
    // -------------------------
    // All rows of A stream simultaneously, one column k per cycle.
    // ain[r] = A[r][k] — row r of A, column k.
    // Skew registers inside the array handle diagonal alignment.
    // After DIM data cycles, flush with zeros for:
    //   (DIM-1) activation skew drain + (DIM-1) horizontal propagation
    for (int k = 0; k < DIM + 2*(DIM-1); k++) begin
        for (int r = 0; r < DIM; r++)
            ain[r] = (k < DIM) ? A[r][k] : '0;
        $display("Cycle %0d: k=%0d ain=[%0d,%0d]",
                 cycle_count, k, ain[0], ain[1]);
        @(posedge clk);
    end

    // -------------------------
    // Phase 4: Drain — Capture Each Row as it Becomes Valid
    // -------------------------
    // Row i of C is valid at the bottom of the array
    // (DIM-1) psum pipeline cycles after its last MAC fires.
    // Row 0 drains first, row DIM-1 drains last, one cycle apart.
    repeat(DIM-1) @(posedge clk);

    for (int i = 0; i < DIM; i++) begin
        // Each successive row needs 1 more cycle for psum pipeline
        @(posedge clk);
        $display("Cycle %0d: capturing C row %0d cout=[%0d,%0d]",
                 cycle_count, i, cout[0], cout[1]);
        for (int j = 0; j < DIM; j++)
            C_hw[i][j] = cout[j];
        @(posedge clk);
    end

    // -------------------------
    // Phase 5: Compare
    // -------------------------
    $display("--- SW reference ---");
    for (int i = 0; i < DIM; i++)
        for (int j = 0; j < DIM; j++)
            $display("  C_sw[%0d][%0d] = %0d", i, j, C_sw[i][j]);

    $display("--- HW result ---");
    for (int i = 0; i < DIM; i++)
        for (int j = 0; j < DIM; j++)
            $display("  C_hw[%0d][%0d] = %0d", i, j, C_hw[i][j]);

    $display("--- Comparison ---");
    for (int i = 0; i < DIM; i++)
        for (int j = 0; j < DIM; j++) begin
            if (C_hw[i][j] !== C_sw[i][j])
                $display("MISMATCH C[%0d][%0d]: hw=%0d sw=%0d",
                         i, j, C_hw[i][j], C_sw[i][j]);
            else
                $display("MATCH    C[%0d][%0d]: hw=%0d sw=%0d",
                         i, j, C_hw[i][j], C_sw[i][j]);
        end

    $finish;
end
endmodule

VerilogTest/outputs/wave.vcd
$version Generated by VerilatedVcd $end
$timescale 1ns $end
 $scope module TOP $end
  $scope module mac_array_tb $end
   $var wire 32 '! DIM [31:0] $end
   $var wire 32 (! LEN [31:0] $end
   $var wire 32 )! PSUM_WIDTH [31:0] $end
   $var wire 32 *! PERIOD [31:0] $end
   $var wire 32 +! LATENCY [31:0] $end
   $var wire 1 !! clk $end
   $var wire 1 # nrst $end
   $var wire 1 $ load_weight $end
   $var wire 1 % clear_psum $end
   $var wire 16 & ain[0] [15:0] $end
   $var wire 16 ' ain[1] [15:0] $end
   $var wire 16 ( win[0] [15:0] $end
   $var wire 16 ) win[1] [15:0] $end
   $var wire 32 * cin[0] [31:0] $end
   $var wire 32 + cin[1] [31:0] $end
   $var wire 16 Q aout[0] [15:0] $end
   $var wire 16 R aout[1] [15:0] $end
   $var wire 32 S cout[0] [31:0] $end
   $var wire 32 T cout[1] [31:0] $end
   $var wire 16 , A[0][0] [15:0] $end
   $var wire 16 - A[0][1] [15:0] $end
   $var wire 16 . A[1][0] [15:0] $end
   $var wire 16 / A[1][1] [15:0] $end
   $var wire 16 0 B[0][0] [15:0] $end
   $var wire 16 1 B[0][1] [15:0] $end
   $var wire 16 2 B[1][0] [15:0] $end
   $var wire 16 3 B[1][1] [15:0] $end
   $var wire 32 4 C_sw[0][0] [31:0] $end
   $var wire 32 5 C_sw[0][1] [31:0] $end
   $var wire 32 6 C_sw[1][0] [31:0] $end
   $var wire 32 7 C_sw[1][1] [31:0] $end
   $var wire 32 8 C_hw[0][0] [31:0] $end
   $var wire 32 9 C_hw[0][1] [31:0] $end
   $var wire 32 : C_hw[1][0] [31:0] $end
   $var wire 32 ; C_hw[1][1] [31:0] $end
   $var wire 1 ,! valid_in_row[0] $end
   $var wire 1 -! valid_in_row[1] $end
   $var wire 32 .! flush_cycles [31:0] $end
   $var wire 32 U cycle_count [31:0] $end
   $scope module dut $end
    $var wire 32 '! DIM [31:0] $end
    $var wire 32 (! LEN [31:0] $end
    $var wire 32 )! PSUM_WIDTH [31:0] $end
    $var wire 1 !! clk $end
    $var wire 1 # nrst $end
    $var wire 1 $ load_weight $end
    $var wire 1 % clear_psum $end
    $var wire 16 & ain[0] [15:0] $end
    $var wire 16 ' ain[1] [15:0] $end
    $var wire 16 ( win[0] [15:0] $end
    $var wire 16 ) win[1] [15:0] $end
    $var wire 32 * cin[0] [31:0] $end
    $var wire 32 + cin[1] [31:0] $end
    $var wire 16 Q aout[0] [15:0] $end
    $var wire 16 R aout[1] [15:0] $end
    $var wire 32 S cout[0] [31:0] $end
    $var wire 32 T cout[1] [31:0] $end
    $var wire 16 "! ain_skewed[0] [15:0] $end
    $var wire 16 #! ain_skewed[1] [15:0] $end
    $var wire 1 $! lw_skewed[0] $end
    $var wire 1 %! lw_skewed[1] $end
    $var wire 1 /! lw_pipe [0:0] $end
    $var wire 16 V a_sig[0][0] [15:0] $end
    $var wire 16 W a_sig[0][1] [15:0] $end
    $var wire 16 X a_sig[1][0] [15:0] $end
    $var wire 16 Y a_sig[1][1] [15:0] $end
    $var wire 16 Z w_sig[0][0] [15:0] $end
    $var wire 16 [ w_sig[0][1] [15:0] $end
    $var wire 16 \ w_sig[1][0] [15:0] $end
    $var wire 16 ] w_sig[1][1] [15:0] $end
    $var wire 32 ^ psum_sig[0][0] [31:0] $end
    $var wire 32 _ psum_sig[0][1] [31:0] $end
    $var wire 32 ` psum_sig[1][0] [31:0] $end
    $var wire 32 a psum_sig[1][1] [31:0] $end
    $var wire 1 b lw_d1 $end
    $var wire 1 c lw_d2 $end
    $scope module row[0] $end
     $scope module col[0] $end
      $var wire 16 < a_in_local [15:0] $end
      $var wire 16 = w_in_local [15:0] $end
      $var wire 32 > psum_in_local [31:0] $end
      $var wire 32 0! psum_pipe1 [31:0] $end
      $scope module mac_inst $end
       $var wire 32 (! LEN [31:0] $end
       $var wire 32 )! PSUM_WIDTH [31:0] $end
       $var wire 1 !! clk $end
       $var wire 1 # nrst $end
       $var wire 1 $ load_weight $end
       $var wire 1 % clear_psum $end
       $var wire 16 < a_in [15:0] $end
       $var wire 16 = w_in [15:0] $end
       $var wire 32 > psum_in [31:0] $end
       $var wire 16 d a_out [15:0] $end
       $var wire 16 e w_out [15:0] $end
       $var wire 32 f psum_out [31:0] $end
       $var wire 16 g weight_reg [15:0] $end
       $var wire 16 e w_out_reg [15:0] $end
       $var wire 32 &! product [31:0] $end
       $var wire 32 &! product_ext [31:0] $end
       $var wire 1 1! valid_reg $end
       $var wire 32 f psum_reg [31:0] $end
       $var wire 16 d a_out_reg [15:0] $end
      $upscope $end
     $upscope $end
     $scope module col[1] $end
      $var wire 16 h a_in_local [15:0] $end
      $var wire 16 ? w_in_local [15:0] $end
      $var wire 32 @ psum_in_local [31:0] $end
      $var wire 32 2! psum_pipe1 [31:0] $end
      $scope module mac_inst $end
       $var wire 32 (! LEN [31:0] $end
       $var wire 32 )! PSUM_WIDTH [31:0] $end
       $var wire 1 !! clk $end
       $var wire 1 # nrst $end
       $var wire 1 $ load_weight $end
       $var wire 1 % clear_psum $end
       $var wire 16 h a_in [15:0] $end
       $var wire 16 ? w_in [15:0] $end
       $var wire 32 @ psum_in [31:0] $end
       $var wire 16 i a_out [15:0] $end
       $var wire 16 j w_out [15:0] $end
       $var wire 32 k psum_out [31:0] $end
       $var wire 16 l weight_reg [15:0] $end
       $var wire 16 j w_out_reg [15:0] $end
       $var wire 32 m product [31:0] $end
       $var wire 32 m product_ext [31:0] $end
       $var wire 1 3! valid_reg $end
       $var wire 32 k psum_reg [31:0] $end
       $var wire 16 i a_out_reg [15:0] $end
      $upscope $end
     $upscope $end
    $upscope $end
    $scope module row[1] $end
     $scope module col[0] $end
      $var wire 16 n a_in_local [15:0] $end
      $var wire 16 o w_in_local [15:0] $end
      $var wire 32 p psum_in_local [31:0] $end
      $var wire 32 p psum_pipe1 [31:0] $end
      $scope module mac_inst $end
       $var wire 32 (! LEN [31:0] $end
       $var wire 32 )! PSUM_WIDTH [31:0] $end
       $var wire 1 !! clk $end
       $var wire 1 # nrst $end
       $var wire 1 b load_weight $end
       $var wire 1 % clear_psum $end
       $var wire 16 n a_in [15:0] $end
       $var wire 16 o w_in [15:0] $end
       $var wire 32 p psum_in [31:0] $end
       $var wire 16 q a_out [15:0] $end
       $var wire 16 r w_out [15:0] $end
       $var wire 32 s psum_out [31:0] $end
       $var wire 16 t weight_reg [15:0] $end
       $var wire 16 r w_out_reg [15:0] $end
       $var wire 32 u product [31:0] $end
       $var wire 32 u product_ext [31:0] $end
       $var wire 1 4! valid_reg $end
       $var wire 32 s psum_reg [31:0] $end
       $var wire 16 q a_out_reg [15:0] $end
      $upscope $end
     $upscope $end
     $scope module col[1] $end
      $var wire 16 v a_in_local [15:0] $end
      $var wire 16 w w_in_local [15:0] $end
      $var wire 32 x psum_in_local [31:0] $end
      $var wire 32 x psum_pipe1 [31:0] $end
      $scope module mac_inst $end
       $var wire 32 (! LEN [31:0] $end
       $var wire 32 )! PSUM_WIDTH [31:0] $end
       $var wire 1 !! clk $end
       $var wire 1 # nrst $end
       $var wire 1 b load_weight $end
       $var wire 1 % clear_psum $end
       $var wire 16 v a_in [15:0] $end
       $var wire 16 w w_in [15:0] $end
       $var wire 32 x psum_in [31:0] $end
       $var wire 16 y a_out [15:0] $end
       $var wire 16 z w_out [15:0] $end
       $var wire 32 { psum_out [31:0] $end
       $var wire 16 | weight_reg [15:0] $end
       $var wire 16 z w_out_reg [15:0] $end
       $var wire 32 } product [31:0] $end
       $var wire 32 } product_ext [31:0] $end
       $var wire 1 5! valid_reg $end
       $var wire 32 { psum_reg [31:0] $end
       $var wire 16 y a_out_reg [15:0] $end
      $upscope $end
     $upscope $end
    $upscope $end
    $scope module skew_row[1] $end
     $var wire 16 ~ ain_skew_chain[0] [15:0] $end
    $upscope $end
    $scope module unnamedblk1 $end
     $var wire 32 6! k [31:0] $end
    $upscope $end
    $scope module unnamedblk2 $end
     $var wire 32 6! k [31:0] $end
    $upscope $end
   $upscope $end
   $scope module unnamedblk11 $end
    $var wire 32 A i [31:0] $end
   $upscope $end
   $scope module unnamedblk12 $end
    $var wire 32 B k [31:0] $end
    $scope module unnamedblk13 $end
     $var wire 32 C r [31:0] $end
    $upscope $end
   $upscope $end
   $scope module unnamedblk14 $end
    $var wire 32 D i [31:0] $end
    $scope module unnamedblk15 $end
     $var wire 32 E j [31:0] $end
    $upscope $end
   $upscope $end
   $scope module unnamedblk16 $end
    $var wire 32 F i [31:0] $end
    $scope module unnamedblk17 $end
     $var wire 32 G j [31:0] $end
    $upscope $end
   $upscope $end
   $scope module unnamedblk18 $end
    $var wire 32 H i [31:0] $end
    $scope module unnamedblk19 $end
     $var wire 32 I j [31:0] $end
    $upscope $end
   $upscope $end
   $scope module unnamedblk20 $end
    $var wire 32 J i [31:0] $end
    $scope module unnamedblk21 $end
     $var wire 32 K j [31:0] $end
    $upscope $end
   $upscope $end
   $scope module unnamedblk6 $end
    $var wire 32 L i [31:0] $end
    $scope module unnamedblk7 $end
     $var wire 32 M j [31:0] $end
    $upscope $end
   $upscope $end
   $scope module unnamedblk8 $end
    $var wire 32 N col [31:0] $end
   $upscope $end
   $scope module unnamedblk9 $end
    $var wire 32 O row [31:0] $end
    $scope module unnamedblk10 $end
     $var wire 32 P col [31:0] $end
    $upscope $end
   $upscope $end
  $upscope $end
 $upscope $end
$enddefinitions $end


#0
0#
0$
0%
b0000000000000000 &
b0000000000000000 '
b0000000000000000 (
b0000000000000000 )
b00000000000000000000000000000000 *
b00000000000000000000000000000000 +
b0000000000000001 ,
b0000000000000010 -
b0000000000000011 .
b0000000000000100 /
b0000000000000001 0
b0000000000000010 1
b0000000000000011 2
b0000000000000100 3
b00000000000000000000000000000111 4
b00000000000000000000000000001010 5
b00000000000000000000000000001111 6
b00000000000000000000000000010110 7
b00000000000000000000000000000000 8
b00000000000000000000000000000000 9
b00000000000000000000000000000000 :
b00000000000000000000000000000000 ;
b0000000000000000 <
b0000000000000000 =
b00000000000000000000000000000000 >
b0000000000000000 ?
b00000000000000000000000000000000 @
b00000000000000000000000000000000 A
b00000000000000000000000000000000 B
b00000000000000000000000000000000 C
b00000000000000000000000000000000 D
b00000000000000000000000000000000 E
b00000000000000000000000000000000 F
b00000000000000000000000000000000 G
b00000000000000000000000000000000 H
b00000000000000000000000000000000 I
b00000000000000000000000000000000 J
b00000000000000000000000000000000 K
b00000000000000000000000000000010 L
b00000000000000000000000000000010 M
b00000000000000000000000000000000 N
b00000000000000000000000000000000 O
b00000000000000000000000000000000 P
b0000000000000000 Q
b0000000000000000 R
b00000000000000000000000000000000 S
b00000000000000000000000000000000 T
b00000000000000000000000000000000 U
b0000000000000000 V
b0000000000000000 W
b0000000000000000 X
b0000000000000000 Y
b0000000000000000 Z
b0000000000000000 [
b0000000000000000 \
b0000000000000000 ]
b00000000000000000000000000000000 ^
b00000000000000000000000000000000 _
b00000000000000000000000000000000 `
b00000000000000000000000000000000 a
0b
0c
b0000000000000000 d
b0000000000000000 e
b00000000000000000000000000000000 f
b0000000000000000 g
b0000000000000000 h
b0000000000000000 i
b0000000000000000 j
b00000000000000000000000000000000 k
b0000000000000000 l
b00000000000000000000000000000000 m
b0000000000000000 n
b0000000000000000 o
b00000000000000000000000000000000 p
b0000000000000000 q
b0000000000000000 r
b00000000000000000000000000000000 s
b0000000000000000 t
b00000000000000000000000000000000 u
b0000000000000000 v
b0000000000000000 w
b00000000000000000000000000000000 x
b0000000000000000 y
b0000000000000000 z
b00000000000000000000000000000000 {
b0000000000000000 |
b00000000000000000000000000000000 }
b0000000000000000 ~
0!!
b0000000000000000 "!
b0000000000000000 #!
0$!
0%!
b00000000000000000000000000000000 &!
b00000000000000000000000000000010 '!
b00000000000000000000000000010000 (!
b00000000000000000000000000100000 )!
b00000000000000000000000000001010 *!
b00000000000000000000000000000101 +!
0,!
0-!
b00000000000000000000000000000000 .!
0/!
b00000000000000000000000000000000 0!
01!
b00000000000000000000000000000000 2!
03!
04!
05!
b00000000000000000000000000000010 6!
#5
1!!
#10
0!!
#15
1#
b00000000000000000000000000000001 U
1!!
#20
0!!
#25
1$
b0000000000000001 (
b0000000000000010 )
b0000000000000001 =
b0000000000000010 ?
b00000000000000000000000000000010 N
b00000000000000000000000000000010 U
b0000000000000001 Z
b0000000000000010 [
1b
b0000000000000001 e
b0000000000000001 g
b0000000000000010 j
b0000000000000010 l
b0000000000000001 o
b0000000000000010 w
1!!
1$!
1%!
#30
0!!
#35
0$
b00000000000000000000000000000011 U
b0000000000000001 \
b0000000000000010 ]
0b
1c
b0000000000000001 r
b0000000000000001 t
b0000000000000010 z
b0000000000000010 |
1!!
0$!
0%!
#40
0!!
#45
b0000000000000011 (
b0000000000000100 )
b0000000000000011 =
b0000000000000100 ?
b00000000000000000000000000000010 P
b00000000000000000000000000000100 U
b0000000000000011 Z
b0000000000000100 [
0c
b0000000000000011 e
b0000000000000100 j
b0000000000000011 o
b0000000000000100 w
1!!
#50
0!!
#55
b00000000000000000000000000000010 O
b00000000000000000000000000000101 U
b0000000000000011 \
b0000000000000100 ]
b0000000000000011 r
b0000000000000100 z
1!!
#60
0!!
#65
b00000000000000000000000000000110 U
1!!
#70
0!!
#75
b00000000000000000000000000000111 U
1!!
#80
0!!
#85
1%
b00000000000000000000000000000010 A
b00000000000000000000000000001000 U
1!!
#90
0!!
#95
0%
b0000000000000001 &
b0000000000000011 '
b0000000000000001 <
b00000000000000000000000000000010 C
b00000000000000000000000000001001 U
b0000000000000001 V
b00000000000000000000000000000001 ^
b0000000000000001 d
b00000000000000000000000000000001 f
b0000000000000001 h
b00000000000000000000000000000010 m
b0000000000000011 n
b00000000000000000000000000000011 u
b0000000000000011 ~
1!!
b0000000000000001 "!
b0000000000000011 #!
b00000000000000000000000000000001 &!
#100
0!!
#105
b0000000000000010 &
b0000000000000100 '
b0000000000000010 <
b00000000000000000000000000000001 B
b0000000000000001 Q
b00000000000000000000000000000011 S
b00000000000000000000000000001010 U
b0000000000000010 V
b0000000000000001 W
b0000000000000011 X
b00000000000000000000000000000010 ^
b00000000000000000000000000000010 _
b00000000000000000000000000000011 `
b0000000000000010 d
b00000000000000000000000000000010 f
b0000000000000010 h
b0000000000000001 i
b00000000000000000000000000000010 k
b00000000000000000000000000000100 m
b0000000000000100 n
b00000000000000000000000000000001 p
b0000000000000011 q
b00000000000000000000000000000011 s
b00000000000000000000000000000100 u
b0000000000000011 v
b00000000000000000000000000000110 }
b0000000000000100 ~
1!!
b0000000000000010 "!
b0000000000000100 #!
b00000000000000000000000000000010 &!
#110
0!!
#115
b0000000000000000 &
b0000000000000000 '
b0000000000000000 <
b00000000000000000000000000000010 B
b0000000000000010 Q
b0000000000000011 R
b00000000000000000000000000000101 S
b00000000000000000000000000000110 T
b00000000000000000000000000001011 U
b0000000000000000 V
b0000000000000010 W
b0000000000000100 X
b0000000000000011 Y
b00000000000000000000000000000000 ^
b00000000000000000000000000000100 _
b00000000000000000000000000000101 `
b00000000000000000000000000000110 a
b0000000000000000 d
b00000000000000000000000000000000 f
b0000000000000000 h
b0000000000000010 i
b00000000000000000000000000000100 k
b00000000000000000000000000000000 m
b0000000000000000 n
b00000000000000000000000000000010 p
b0000000000000100 q
b00000000000000000000000000000101 s
b00000000000000000000000000000000 u
b0000000000000100 v
b00000000000000000000000000000010 x
b0000000000000011 y
b00000000000000000000000000000110 {
b00000000000000000000000000001000 }
b0000000000000000 ~
1!!
b0000000000000000 "!
b0000000000000000 #!
b00000000000000000000000000000000 &!
#120
0!!
#125
b00000000000000000000000000000011 B
b0000000000000000 Q
b0000000000000100 R
b00000000000000000000000000000010 S
b00000000000000000000000000001010 T
b00000000000000000000000000001100 U
b0000000000000000 W
b0000000000000000 X
b0000000000000100 Y
b00000000000000000000000000000000 _
b00000000000000000000000000000010 `
b00000000000000000000000000001010 a
b0000000000000000 i
b00000000000000000000000000000000 k
b00000000000000000000000000000000 p
b0000000000000000 q
b00000000000000000000000000000010 s
b0000000000000000 v
b00000000000000000000000000000100 x
b0000000000000100 y
b00000000000000000000000000001010 {
b00000000000000000000000000000000 }
1!!
#130
0!!
#135
b00000000000000000000000000000100 B
b0000000000000000 R
b00000000000000000000000000000000 S
b00000000000000000000000000000100 T
b00000000000000000000000000001101 U
b0000000000000000 Y
b00000000000000000000000000000000 `
b00000000000000000000000000000100 a
b00000000000000000000000000000000 s
b00000000000000000000000000000000 x
b0000000000000000 y
b00000000000000000000000000000100 {
1!!
#140
0!!
#145
b00000000000000000000000000000000 T
b00000000000000000000000000001110 U
b00000000000000000000000000000000 a
b00000000000000000000000000000000 {
1!!
#150
0!!
#155
b00000000000000000000000000000010 E
b00000000000000000000000000001111 U
1!!
#160
0!!
#165
b00000000000000000000000000000001 D
b00000000000000000000000000010000 U
1!!
#170
0!!
#175
b00000000000000000000000000010001 U
1!!
#180
0!!
#185
b00000000000000000000000000000010 D
b00000000000000000000000000000010 F
b00000000000000000000000000000010 G
b00000000000000000000000000000010 H
b00000000000000000000000000000010 I
b00000000000000000000000000000010 J
b00000000000000000000000000000010 K
b00000000000000000000000000010010 U
1!!
